<!-- material sources -->
<sources>


	<boundary_source name="electrons" type="maxwellian">
	<boundary>inlet</boundary>
	<material>e-</material>
	<current>0.1</current> <!-- Python code-->
	<temperature>23209.03624</temperature> <!-- 2ev -->
	<v_drift>1e3</v_drift>
	<!-- <start_it> 500 </start_it> -->
</boundary_source>


	<boundary_source name="neutral_gas" type="maxwellian">
	<boundary>neutral_inlet</boundary>
	<material>Kr</material>
	<mdot>1e-6</mdot> <!-- Python code -->
	<temperature>278</temperature>
	<v_drift>1e3</v_drift> <!-- Python code -->
</boundary_source>

<!-- Use restart data to load the density profile. Python code
does not work for this-->
<!--
<boundary_source name="neutral_gas" type="ambient">
<enforce>pressure</enforce>
<material>Kr</material>
<boundary>neutral_inlet</boundary>
<drift_velocity>0,0,0</drift_velocity>
<temperature>293.0</temperature>
<total_pressure>1.0</total_pressure>
</boundary_source> -->


</sources>
